[
        {
                "states": "Alabama", 
                "state abbreviation": "AL", 
                "vacc_rate": "90.6"
        }, 
        {
                "states": "Arizona", 
                "state abbreviation": "AZ", 
                "vacc_rate": "92.9"
        }, 
        {
                "states": "Arkansas", 
                "state abbreviation": "AR", 
                "vacc_rate": "94.2"
        }, 
        {
                "states": "California", 
                "state abbreviation": "CA", 
                "vacc_rate": "96.5"
        }, 
        {
                "states": "Colorado", 
                "state abbreviation": "CO", 
                "vacc_rate": "87.4"
        }, 
        {
                "states": "Connecticut", 
                "state abbreviation": "CT", 
                "vacc_rate": "95.9"
        }, 
        {
                "states": "Delaware", 
                "state abbreviation": "DE", 
                "vacc_rate": "97.8"
        }, 
        {
                "states": "Florida", 
                "state abbreviation": "FL", 
                "vacc_rate": "93.8"
        }, 
        {
                "states": "Georgia", 
                "state abbreviation": "GA", 
                "vacc_rate": "93.6"
        }, 
        {
                "states": "Hawaii", 
                "state abbreviation": "HI", 
                "vacc_rate": "91.5"
        }, 
        {
                "states": "Idaho", 
                "state abbreviation": "ID", 
                "vacc_rate": "89.5"
        }, 
        {
                "states": "Illinois", 
                "state abbreviation": "IL", 
                "vacc_rate": "94.7"
        }, 
        {
                "states": "Indiana", 
                "state abbreviation": "IN", 
                "vacc_rate": "91.2"
        }, 
        {
                "states": "Iowa", 
                "state abbreviation": "IA", 
                "vacc_rate": "93.3"
        }, 
        {
                "states": "Kansas", 
                "state abbreviation": "KS", 
                "vacc_rate": "90.8"
        }, 
        {
                "states": "Kentucky", 
                "state abbreviation": "KY", 
                "vacc_rate": "93.4"
        }, 
        {
                "states": "Louisiana", 
                "state abbreviation": "LA", 
                "vacc_rate": "95.5"
        }, 
        {
                "states": "Maine", 
                "state abbreviation": "ME", 
                "vacc_rate": "93.8"
        }, 
        {
                "states": "Maryland", 
                "state abbreviation": "MD", 
                "vacc_rate": "97.4"
        }, 
        {
                "states": "Massachusetts", 
                "state abbreviation": "MA", 
                "vacc_rate": "96.9"
        }, 
        {
                "states": "Michigan", 
                "state abbreviation": "MI", 
                "vacc_rate": "94.6"
        }, 
        {
                "states": "Minnesota", 
                "state abbreviation": "MN", 
                "vacc_rate": "92.6"
        }, 
        {
                "states": "Mississippi", 
                "state abbreviation": "MS", 
                "vacc_rate": "99.2"
        }, 
        {
                "states": "Missouri", 
                "state abbreviation": "MO", 
                "vacc_rate": "94.8"
        }, 
        {
                "states": "Montana", 
                "state abbreviation": "MT", 
                "vacc_rate": "93.3"
        }, 
        {
                "states": "Nebraska", 
                "state abbreviation": "NE", 
                "vacc_rate": "96.9"
        }, 
        {
                "states": "Nevada", 
                "state abbreviation": "NV", 
                "vacc_rate": "95.1"
        }, 
        {
                "states": "New Hampshire", 
                "state abbreviation": "NH", 
                "vacc_rate": "91.8"
        }, 
        {
                "states": "New Jersey", 
                "state abbreviation": "NNJ", 
                "vacc_rate": "95"
        }, 
        {
                "states": "New Mexico", 
                "state abbreviation": "NM", 
                "vacc_rate": "96.1"
        }, 
        {
                "states": "New York", 
                "state abbreviation": "NY", 
                "vacc_rate": "97.2"
        }, 
        {
                "states": "North Carolina", 
                "state abbreviation": "NC", 
                "vacc_rate": "93.2"
        }, 
        {
                "states": "North Dakota", 
                "state abbreviation": "ND", 
                "vacc_rate": "93.6"
        }, 
        {
                "states": "Ohio", 
                "state abbreviation": "OH", 
                "vacc_rate": "91.6"
        }, 
        {
                "states": "Oklahoma", 
                "state abbreviation": "OK", 
                "vacc_rate": "92.2"
        }, 
        {
                "states": "Oregon", 
                "state abbreviation": "OR", 
                "vacc_rate": "93"
        }, 
        {
                "states": "Pennsylvania", 
                "state abbreviation": "PA", 
                "vacc_rate": "96.4"
        }, 
        {
                "states": "Rhode Island", 
                "state abbreviation": "RI", 
                "vacc_rate": "97.4"
        }, 
        {
                "states": "South Carolina", 
                "state abbreviation": "SC", 
                "vacc_rate": "94.2"
        }, 
        {
                "states": "South Dakota", 
                "state abbreviation": "SD", 
                "vacc_rate": "96.2"
        }, 
        {
                "states": "Tennessee", 
                "state abbreviation": "TN", 
                "vacc_rate": "96.5"
        }, 
        {
                "states": "Texas", 
                "state abbreviation": "TX", 
                "vacc_rate": "96.9"
        }, 
        {
                "states": "Utah", 
                "state abbreviation": "UT", 
                "vacc_rate": "92.8"
        }, 
        {
                "states": "Vermont", 
                "state abbreviation": "VT", 
                "vacc_rate": "93"
        }, 
        {
                "states": "Virginia", 
                "state abbreviation": "VA", 
                "vacc_rate": "95"
        }, 
        {
                "states": "Washington", 
                "state abbreviation": "WA", 
                "vacc_rate": "90.8"
        }, 
        {
                "states": "West Virginia", 
                "state abbreviation": "WV", 
                "vacc_rate": "98.8"
        }, 
        {
                "states": "Wisconsin", 
                "state abbreviation": "WI", 
                "vacc_rate": "92.6"
        }, 
        {
                "states": "Wyoming", 
                "state abbreviation": "WY", 
                "vacc_rate": "95.1"
        }
]